wagtail_grafl/__init__.py
wagtail_grafl/apps.py
wagtail_grafl/blocks.py
wagtail_grafl/config.py
wagtail_grafl/models.py
wagtail_grafl/utils.py
wagtail_grafl/widgets.py
wagtail_grafl/templates/wagtail_grafl/blocks/grafl.html
wagtail_grafl-0.0.2.dist-info/LICENSE
wagtail_grafl-0.0.2.dist-info/METADATA
wagtail_grafl-0.0.2.dist-info/WHEEL
wagtail_grafl-0.0.2.dist-info/top_level.txt
wagtail_grafl-0.0.2.dist-info/RECORD
