Metadata-Version: 2.1
Name: wagtail_grafl
Version: 0.0.2
Summary: grafl.io integration for Wagtail CMS
Home-page: https://github.com/cursive-works/wagtail-grafl
Author: Martin Swarbrick
Author-email: martin.swarbrick@cursive.works
License: MIT
Keywords: WAGTAIL,GRAFL,STREAMFIELD,WAGTAIL_GRAFL,WAGTAIL CMS
Classifier: Development Status :: 3 - Alpha
Classifier: Environment :: Web Environment
Classifier: Framework :: Django
Classifier: Intended Audience :: Developers
Classifier: License :: OSI Approved :: MIT License
Classifier: Operating System :: OS Independent
Classifier: Programming Language :: Python
Classifier: Programming Language :: Python :: 3.6
Classifier: Programming Language :: Python :: 3.7
Classifier: Programming Language :: Python :: 3.8
Classifier: Programming Language :: Python :: 3.9
Classifier: Topic :: Internet :: WWW/HTTP
Classifier: Topic :: Internet :: WWW/HTTP :: Dynamic Content
Classifier: Topic :: Software Development
License-File: LICENSE
